render_engine_json/__init__.py
render_engine_json/parsers.py
render_engine_json-2023.12.2.dist-info/METADATA
render_engine_json-2023.12.2.dist-info/WHEEL
render_engine_json-2023.12.2.dist-info/top_level.txt
render_engine_json-2023.12.2.dist-info/RECORD
