Metadata-Version: 2.1
Name: render-engine-json
Version: 2023.12.2
Summary: JSON Parser and Collection for Render Engine
Project-URL: homepage, https://github.com/kjaymiller/render_engine_json/
Project-URL: repository, https://github.com/kjaymiller/render_engine_json/
Requires-Python: >=3.10
Requires-Dist: render-engine >=2023.12.1b3
Requires-Dist: python-slugify
Provides-Extra: dev
Requires-Dist: pytest ; extra == 'dev'
